{"name":"Cartografia colaborativa","tagline":"Cartografia abierta a la colaboración ciudadana (CrowdMapping)","body":"﻿## [![Icono](http://www.iderioja.larioja.org/imagenes/logo_iderioja_56x70.gif)](http://www.iderioja.org)     [Cartografía colaborativa](https://github.com/iderioja/cartografia_colaborativa)\r\n\r\nRepositorio creado para recoger datos geográficos generados por los usuarios de forma colaborativa.\r\n\r\nGitHub permite la visualización cartográfica de datos geográficos almacenados en formato GeoJson.\r\n\r\nLos datos se pueden editar externamente o bien hacerlo directamente dentro del entorno GitHub mediante edición alfanumérica.\r\n\r\nGoogle Chrome ofrece la [extensión geojson.io](https://chrome.google.com/webstore/detail/geojsonio/oibjgofbhldcajfamjganpeacipebckp) que provee un conjunto de herramientas que permite editar gráficamente ficheros GeoJson dentro del entorno GitHub.\r\n\r\nLos datos geográficos de interés para el Gobierno de La Rioja podrán pasar a formar parte de la base de datos espacial IDErioja, siempre y cuando cumplan las condiciones métricas y de exactitud necesarias para la escala de referencia.\r\n\r\nPara que la participación en este proyecto te resulte un poco más fácil, puedes consultar la **[\"Guía para la edición colaborativa de la cartografía del Gobierno de La Rioja\"](https://github.com/iderioja/cartografia_colaborativa/blob/master/guia_edicion_cartografia_colaborativa.md)** que desde este mismo repositorio ponemos a tu disposición.\r\n\r\n\r\nEl Equipo Técnico IDErioja\r\n","google":"","note":"Don't delete this file! It's used internally to help with page regeneration."}